Workbook

Sheet assumptions
A1: starting_customers | B1: 1000
A2: ARPU | B2: 499
A3: Monthly_growth_rate | B3: 0.08
A4: Monthly_churn_rate | B4: 0.04
A5: variable_cost_per_customer | B5: 80
A6: fixed_monthly_cost | B6: 450000
A7: opening_cash | B7: 2500000

Sheet monthly_projection
A1: Month | B1: Customers | C1: Revenue | D1: Variable_cost | E1: Fixed_cost | F1: Total_cost | G1: Profit
A2: month 1 | B2: =assumptions!$B$1 -> 1000 | C2: =B2*assumptions!B2 -> 499000 | D2: =B2 * assumptions!$B$5 -> 80000 | E2: =assumptions!$B$6 -> 450000 | F2: =D2 + E2 -> 530000 | G2: =C2 - F2 -> -31000
A3: month 2 | B3: =B2*(1+assumptions!B3 -assumptions!B4) -> 1040 | C3: =B3*assumptions!B2 -> 518960 | D3: =B3 * assumptions!$B$5 -> 83200 | E3: =assumptions!$B$6 -> 450000 | F3: =D3 + E3 -> 533200 | G3: =C3 - F3 -> -14240
A4: month 3 | B4: =MAX(0, ROUNDDOWN(B3*(1 + assumptions!$B$3 - assumptions!$B$4), 0)) -> 1081 | C4: =B4*assumptions!B2 -> 539419 | D4: =B4 * assumptions!$B$5 -> 86480 | E4: =assumptions!$B$6 -> 450000 | F4: =D4 + E4 -> 536480 | G4: =C4 - F4 -> 2939
A5: month 4 | B5: =MAX(0, ROUNDDOWN(B4*(1 + assumptions!$B$3 - assumptions!$B$4), 0)) -> 1124 | C5: =B5*assumptions!B2 -> 560876 | D5: =B5 * assumptions!$B$5 -> 89920 | E5: =assumptions!$B$6 -> 450000 | F5: =D5 + E5 -> 539920 | G5: =C5 - F5 -> 20956
A6: month 5 | B6: =MAX(0, ROUNDDOWN(B5*(1 + assumptions!$B$3 - assumptions!$B$4), 0)) -> 1168 | C6: =B6*assumptions!B2 -> 582832 | D6: =B6 * assumptions!$B$5 -> 93440 | E6: =assumptions!$B$6 -> 450000 | F6: =D6 + E6 -> 543440 | G6: =C6 - F6 -> 39392
A7: month 6 | B7: =MAX(0, ROUNDDOWN(B6*(1 + assumptions!$B$3 - assumptions!$B$4), 0)) -> 1214 | C7: =B7*assumptions!B2 -> 605786 | D7: =B7 * assumptions!$B$5 -> 97120 | E7: =assumptions!$B$6 -> 450000 | F7: =D7 + E7 -> 547120 | G7: =C7 - F7 -> 58666
A8: month 7 | B8: =MAX(0, ROUNDDOWN(B7*(1 + assumptions!$B$3 - assumptions!$B$4), 0)) -> 1262 | C8: =B8*assumptions!B2 -> 629738 | D8: =B8 * assumptions!$B$5 -> 100960 | E8: =assumptions!$B$6 -> 450000 | F8: =D8 + E8 -> 550960 | G8: =C8 - F8 -> 78778
A9: month 8 | B9: =MAX(0, ROUNDDOWN(B8*(1 + assumptions!$B$3 - assumptions!$B$4), 0)) -> 1312 | C9: =B9*assumptions!B2 -> 654688 | D9: =B9 * assumptions!$B$5 -> 104960 | E9: =assumptions!$B$6 -> 450000 | F9: =D9 + E9 -> 554960 | G9: =C9 - F9 -> 99728
A10: month 9 | B10: =MAX(0, ROUNDDOWN(B9*(1 + assumptions!$B$3 - assumptions!$B$4), 0)) -> 1364 | C10: =B10*assumptions!B2 -> 680636 | D10: =B10 * assumptions!$B$5 -> 109120 | E10: =assumptions!$B$6 -> 450000 | F10: =D10 + E10 -> 559120 | G10: =C10 - F10 -> 121516
A11: month 10 | B11: =MAX(0, ROUNDDOWN(B10*(1 + assumptions!$B$3 - assumptions!$B$4), 0)) -> 1418 | C11: =B11*assumptions!B2 -> 707582 | D11: =B11 * assumptions!$B$5 -> 113440 | E11: =assumptions!$B$6 -> 450000 | F11: =D11 + E11 -> 563440 | G11: =C11 - F11 -> 144142
A12: month 11 | B12: =MAX(0, ROUNDDOWN(B11*(1 + assumptions!$B$3 - assumptions!$B$4), 0)) -> 1474 | C12: =B12*assumptions!B2 -> 735526 | D12: =B12 * assumptions!$B$5 -> 117920 | E12: =assumptions!$B$6 -> 450000 | F12: =D12 + E12 -> 567920 | G12: =C12 - F12 -> 167606
A13: month 12 | B13: =MAX(0, ROUNDDOWN(B12*(1 + assumptions!$B$3 - assumptions!$B$4), 0)) -> 1532 | C13: =B13*assumptions!B2 -> 764468 | D13: =B13 * assumptions!$B$5 -> 122560 | E13: =assumptions!$B$6 -> 450000 | F13: =D13 + E13 -> 572560 | G13: =C13 - F13 -> 191908
A14: month 13 | B14: =MAX(0, ROUNDDOWN(B13*(1 + assumptions!$B$3 - assumptions!$B$4), 0)) -> 1593 | C14: =B14*assumptions!B2 -> 794907 | D14: =B14 * assumptions!$B$5 -> 127440 | E14: =assumptions!$B$6 -> 450000 | F14: =D14 + E14 -> 577440 | G14: =C14 - F14 -> 217467
A15: month 14 | B15: =MAX(0, ROUNDDOWN(B14*(1 + assumptions!$B$3 - assumptions!$B$4), 0)) -> 1656 | C15: =B15*assumptions!B2 -> 826344 | D15: =B15 * assumptions!$B$5 -> 132480 | E15: =assumptions!$B$6 -> 450000 | F15: =D15 + E15 -> 582480 | G15: =C15 - F15 -> 243864
A16: month 15 | B16: =MAX(0, ROUNDDOWN(B15*(1 + assumptions!$B$3 - assumptions!$B$4), 0)) -> 1722 | C16: =B16*assumptions!B2 -> 859278 | D16: =B16 * assumptions!$B$5 -> 137760 | E16: =assumptions!$B$6 -> 450000 | F16: =D16 + E16 -> 587760 | G16: =C16 - F16 -> 271518
A17: month 16 | B17: =MAX(0, ROUNDDOWN(B16*(1 + assumptions!$B$3 - assumptions!$B$4), 0)) -> 1790 | C17: =B17*assumptions!B2 -> 893210 | D17: =B17 * assumptions!$B$5 -> 143200 | E17: =assumptions!$B$6 -> 450000 | F17: =D17 + E17 -> 593200 | G17: =C17 - F17 -> 300010
A18: month 17 | B18: =MAX(0, ROUNDDOWN(B17*(1 + assumptions!$B$3 - assumptions!$B$4), 0)) -> 1861 | C18: =B18*assumptions!B2 -> 928639 | D18: =B18 * assumptions!$B$5 -> 148880 | E18: =assumptions!$B$6 -> 450000 | F18: =D18 + E18 -> 598880 | G18: =C18 - F18 -> 329759
A19: month 18 | B19: =MAX(0, ROUNDDOWN(B18*(1 + assumptions!$B$3 - assumptions!$B$4), 0)) -> 1935 | C19: =B19*assumptions!B2 -> 965565 | D19: =B19 * assumptions!$B$5 -> 154800 | E19: =assumptions!$B$6 -> 450000 | F19: =D19 + E19 -> 604800 | G19: =C19 - F19 -> 360765
A20: month 19 | B20: =MAX(0, ROUNDDOWN(B19*(1 + assumptions!$B$3 - assumptions!$B$4), 0)) -> 2012 | C20: =B20*assumptions!B2 -> 1003988 | D20: =B20 * assumptions!$B$5 -> 160960 | E20: =assumptions!$B$6 -> 450000 | F20: =D20 + E20 -> 610960 | G20: =C20 - F20 -> 393028
A21: month 20 | B21: =MAX(0, ROUNDDOWN(B20*(1 + assumptions!$B$3 - assumptions!$B$4), 0)) -> 2092 | C21: =B21*assumptions!B2 -> 1043908 | D21: =B21 * assumptions!$B$5 -> 167360 | E21: =assumptions!$B$6 -> 450000 | F21: =D21 + E21 -> 617360 | G21: =C21 - F21 -> 426548
A22: month 21 | B22: =MAX(0, ROUNDDOWN(B21*(1 + assumptions!$B$3 - assumptions!$B$4), 0)) -> 2175 | C22: =B22*assumptions!B2 -> 1085325 | D22: =B22 * assumptions!$B$5 -> 174000 | E22: =assumptions!$B$6 -> 450000 | F22: =D22 + E22 -> 624000 | G22: =C22 - F22 -> 461325
A23: month 22 | B23: =MAX(0, ROUNDDOWN(B22*(1 + assumptions!$B$3 - assumptions!$B$4), 0)) -> 2262 | C23: =B23*assumptions!B2 -> 1128738 | D23: =B23 * assumptions!$B$5 -> 180960 | E23: =assumptions!$B$6 -> 450000 | F23: =D23 + E23 -> 630960 | G23: =C23 - F23 -> 497778
A24: month 23 | B24: =MAX(0, ROUNDDOWN(B23*(1 + assumptions!$B$3 - assumptions!$B$4), 0)) -> 2352 | C24: =B24*assumptions!B2 -> 1173648 | D24: =B24 * assumptions!$B$5 -> 188160 | E24: =assumptions!$B$6 -> 450000 | F24: =D24 + E24 -> 638160 | G24: =C24 - F24 -> 535488
A25: month 24 | B25: =MAX(0, ROUNDDOWN(B24*(1 + assumptions!$B$3 - assumptions!$B$4), 0)) -> 2446 | C25: =B25*assumptions!B2 -> 1220554 | D25: =B25 * assumptions!$B$5 -> 195680 | E25: =assumptions!$B$6 -> 450000 | F25: =D25 + E25 -> 645680 | G25: =C25 - F25 -> 574874

Sheet cash_flow
A1: Month | B1: Opening_cash | C1: Profit | D1: Funding | E1: Closing_cash | F1: Runway_flag
A2: =monthly_projection!A2 -> month 1 | B2: =assumptions!$B$7 -> 2500000 | C2: =monthly_projection!G2 -> -31000 | D2: =0 -> 0 | E2: =B2 + C2 + D2 -> 2469000 | F2: =IF(E2<0,"Run Out","Alive") -> Alive
A3: =monthly_projection!A3 -> month 2 | B3: =E2 -> 2469000 | C3: =monthly_projection!G3 -> -14240 | D3: =0 -> 0 | E3: =B3 + C3 + D3 -> 2454760 | F3: =IF(E3<0,"Run Out","Alive") -> Alive
A4: =monthly_projection!A4 -> month 3 | B4: =E3 -> 2454760 | C4: =monthly_projection!G4 -> 2939 | D4: =0 -> 0 | E4: =B4 + C4 + D4 -> 2457699 | F4: =IF(E4<0,"Run Out","Alive") -> Alive
A5: =monthly_projection!A5 -> month 4 | B5: =E4 -> 2457699 | C5: =monthly_projection!G5 -> 20956 | D5: =0 -> 0 | E5: =B5 + C5 + D5 -> 2478655 | F5: =IF(E5<0,"Run Out","Alive") -> Alive
A6: =monthly_projection!A6 -> month 5 | B6: =E5 -> 2478655 | C6: =monthly_projection!G6 -> 39392 | D6: =0 -> 0 | E6: =B6 + C6 + D6 -> 2518047 | F6: =IF(E6<0,"Run Out","Alive") -> Alive
A7: =monthly_projection!A7 -> month 6 | B7: =E6 -> 2518047 | C7: =monthly_projection!G7 -> 58666 | D7: 0 | E7: =B7 + C7 + D7 -> 2576713 | F7: =IF(E7<0,"Run Out","Alive") -> Alive
A8: =monthly_projection!A8 -> month 7 | B8: =E7 -> 2576713 | C8: =monthly_projection!G8 -> 78778 | D8: =0 -> 0 | E8: =B8 + C8 + D8 -> 2655491 | F8: =IF(E8<0,"Run Out","Alive") -> Alive
A9: =monthly_projection!A9 -> month 8 | B9: =E8 -> 2655491 | C9: =monthly_projection!G9 -> 99728 | D9: =0 -> 0 | E9: =B9 + C9 + D9 -> 2755219 | F9: =IF(E9<0,"Run Out","Alive") -> Alive
A10: =monthly_projection!A10 -> month 9 | B10: =E9 -> 2755219 | C10: =monthly_projection!G10 -> 121516 | D10: =0 -> 0 | E10: =B10 + C10 + D10 -> 2876735 | F10: =IF(E10<0,"Run Out","Alive") -> Alive
A11: =monthly_projection!A11 -> month 10 | B11: =E10 -> 2876735 | C11: =monthly_projection!G11 -> 144142 | D11: =0 -> 0 | E11: =B11 + C11 + D11 -> 3020877 | F11: =IF(E11<0,"Run Out","Alive") -> Alive
A12: =monthly_projection!A12 -> month 11 | B12: =E11 -> 3020877 | C12: =monthly_projection!G12 -> 167606 | D12: =0 -> 0 | E12: =B12 + C12 + D12 -> 3188483 | F12: =IF(E12<0,"Run Out","Alive") -> Alive
A13: =monthly_projection!A13 -> month 12 | B13: =E12 -> 3188483 | C13: =monthly_projection!G13 -> 191908 | D13: =0 -> 0 | E13: =B13 + C13 + D13 -> 3380391 | F13: =IF(E13<0,"Run Out","Alive") -> Alive
A14: =monthly_projection!A14 -> month 13 | B14: =E13 -> 3380391 | C14: =monthly_projection!G14 -> 217467 | D14: =0 -> 0 | E14: =B14 + C14 + D14 -> 3597858 | F14: =IF(E14<0,"Run Out","Alive") -> Alive
A15: =monthly_projection!A15 -> month 14 | B15: =E14 -> 3597858 | C15: =monthly_projection!G15 -> 243864 | D15: =0 -> 0 | E15: =B15 + C15 + D15 -> 3841722 | F15: =IF(E15<0,"Run Out","Alive") -> Alive
A16: =monthly_projection!A16 -> month 15 | B16: =E15 -> 3841722 | C16: =monthly_projection!G16 -> 271518 | D16: =0 -> 0 | E16: =B16 + C16 + D16 -> 4113240 | F16: =IF(E16<0,"Run Out","Alive") -> Alive
A17: =monthly_projection!A17 -> month 16 | B17: =E16 -> 4113240 | C17: =monthly_projection!G17 -> 300010 | D17: =0 -> 0 | E17: =B17 + C17 + D17 -> 4413250 | F17: =IF(E17<0,"Run Out","Alive") -> Alive
A18: =monthly_projection!A18 -> month 17 | B18: =E17 -> 4413250 | C18: =monthly_projection!G18 -> 329759 | D18: =0 -> 0 | E18: =B18 + C18 + D18 -> 4743009 | F18: =IF(E18<0,"Run Out","Alive") -> Alive
A19: =monthly_projection!A19 -> month 18 | B19: =E18 -> 4743009 | C19: =monthly_projection!G19 -> 360765 | D19: =0 -> 0 | E19: =B19 + C19 + D19 -> 5103774 | F19: =IF(E19<0,"Run Out","Alive") -> Alive
... A25: =monthly_projection!A25 -> month 24 | B25: =E24 -> 7417941 | C25: =monthly_projection!G25 -> 574874 | D25: =0 -> 0 | E25: =B25 + C25 + D25 -> 7992815 | F25: =IF(E25<0,"Run Out","Alive") -> Alive

Sheet KPI_summary
A1: Total revenue | B1: =SUM(monthly_projection!C2:C25) -> 19403615
A2: Total cost | B2: =SUM(monthly_projection!F2:F25) -> 13910800
A3: Net profit | B3: =SUM(monthly_projection!G2:G25) -> 5492815
A4: Average monthly burn rate | B4: =AVERAGEIF(monthly_projection!G2:G25,"<0",monthly_projection!G2:G25)*-1 -> 22620
A5: Cash runaway | B5: ="No Runway Risk (Base Case)" -> No Runway Risk (Base Case)
A6: Break-even month | B6: {=MIN(IF(monthly_projection!G2:G25>=0, monthly_projection!A2:A25))} -> 0
